{
    "id": "linkflow-api-environment",
    "name": "LinkFlow API - Local",
    "values": [
        {
            "key": "base_url",
            "value": "https://linkflow-api.test/api/v1",
            "type": "default",
            "enabled": true
        },
        {
            "key": "admin_url",
            "value": "https://linkflow-api.test/admin",
            "type": "default",
            "enabled": true
        },
        {
            "key": "webhook_base_url",
            "value": "https://linkflow-api.test/api",
            "type": "default",
            "enabled": true
        },
        {
            "key": "access_token",
            "value": "",
            "type": "secret",
            "enabled": true
        },
        {
            "key": "refresh_token",
            "value": "",
            "type": "secret",
            "enabled": true
        },
        {
            "key": "user_id",
            "value": "",
            "type": "default",
            "enabled": true
        },
        {
            "key": "user_email",
            "value": "",
            "type": "default",
            "enabled": true
        },
        {
            "key": "workspace_id",
            "value": "",
            "type": "default",
            "enabled": true
        },
        {
            "key": "workflow_id",
            "value": "",
            "type": "default",
            "enabled": true
        },
        {
            "key": "execution_id",
            "value": "",
            "type": "default",
            "enabled": true
        },
        {
            "key": "credential_id",
            "value": "",
            "type": "default",
            "enabled": true
        },
        {
            "key": "webhook_id",
            "value": "",
            "type": "default",
            "enabled": true
        },
        {
            "key": "webhook_uuid",
            "value": "",
            "type": "default",
            "enabled": true
        },
        {
            "key": "variable_id",
            "value": "",
            "type": "default",
            "enabled": true
        },
        {
            "key": "tag_id",
            "value": "",
            "type": "default",
            "enabled": true
        },
        {
            "key": "plan_id",
            "value": "",
            "type": "default",
            "enabled": true
        },
        {
            "key": "member_id",
            "value": "",
            "type": "default",
            "enabled": true
        },
        {
            "key": "invitation_id",
            "value": "",
            "type": "default",
            "enabled": true
        },
        {
            "key": "invitation_token",
            "value": "",
            "type": "default",
            "enabled": true
        },
        {
            "key": "node_type",
            "value": "http_request",
            "type": "default",
            "enabled": true
        },
        {
            "key": "version_id",
            "value": "",
            "type": "default",
            "enabled": true
        },
        {
            "key": "template_slug",
            "value": "",
            "type": "default",
            "enabled": true
        },
        {
            "key": "credential_type",
            "value": "",
            "type": "default",
            "enabled": true
        },
        {
            "key": "reset_token",
            "value": "",
            "type": "default",
            "enabled": true
        },
        {
            "key": "approval_id",
            "value": "",
            "type": "default",
            "enabled": true
        },
        {
            "key": "runbook_id",
            "value": "",
            "type": "default",
            "enabled": true
        },
        {
            "key": "environment_id",
            "value": "",
            "type": "default",
            "enabled": true
        },
        {
            "key": "from_environment_id",
            "value": "",
            "type": "default",
            "enabled": true
        },
        {
            "key": "to_environment_id",
            "value": "",
            "type": "default",
            "enabled": true
        },
        {
            "key": "compare_execution_id",
            "value": "",
            "type": "default",
            "enabled": true
        },
        {
            "key": "connector_key",
            "value": "",
            "type": "default",
            "enabled": true
        }
    ],
    "_postman_variable_scope": "environment"
}
